<?xml version="1.0" encoding="UTF-8"?>
<ConceptMap xmlns="http://hl7.org/fhir">
    <id value="bfs-encounter-class-to-fhir"/>
    <url value="http://fhir.ch/ig/ch-core/ConceptMap/bfs-encounter-class-to-fhir" />
    <version value="2.0.0"/>
    <name value="BfsEncounterClassToFhir" />
    <title value="BFS Encounter Class to FHIR mapping"/>
    <status value="active"/>
    <experimental value="false"/>
    <date value="2019-04-23"/>
    <publisher value="HL7 Switzerland"/>
    <contact>
        <name value="HL7 Switzerland"/>
        <telecom>
            <system value="url"/>
            <value value="https://www.hl7.ch/"/>
        </telecom>
    </contact>
    <description value="BFS Encounter Class to FHIR mapping"/>
    <jurisdiction>
        <coding>
            <system value="urn:iso:std:iso:3166"/>
            <code value="CH"/>
        </coding>
    </jurisdiction>
    <copyright value="CC0-1.0"/>
    <sourceUri value="http://fhir.ch/ig/ch-core/ValueSet/bfs-medstats-20-encounterclass"/>
    <targetUri value="http://terminology.hl7.org/ValueSet/v3-ActEncounterCode"/>
    <group>
        <source value="http://fhir.ch/ig/ch-core/CodeSystem/bfs-medstats-20-encounterclass"/>
        <target value="http://terminology.hl7.org/CodeSystem/v3-ActCode"/>
        <element>
            <code value="1"/>
            <display value="ambulant"/>
            <target>
                <code value="AMB"/>
                <display value="ambulatory"/>
                <equivalence value="equivalent"/>
            </target>
        </element>
        <element>
            <code value="3"/>
            <display value="stationär"/>
            <target>
                <code value="IMP"/>
                <display value="inpatient encounter"/>
                <equivalence value="equivalent"/>
            </target>
        </element> 
        <element>
            <code value="9"/>
            <display value="unbekannt"/>
            <target>
                <equivalence value="unmatched"/>
            </target>
        </element>
    </group>
</ConceptMap>
