<?xml version="1.0" encoding="UTF-8"?>
<StructureDefinition xmlns="http://hl7.org/fhir">
    <id value="ch-ext-bfs-ms-admitrole"/>
    <url value="http://fhir.ch/ig/ch-core/StructureDefinition/ch-ext-bfs-ms-admitrole"/>
    <version value="1.1.0"/>
    <name value="BfsMsAdmitRole"/>
    <title value="BFS Extension Medical Statistic: Admit Role for Encounter"/>
    <status value="active"/>
    <date value="2019-04-23"/>
    <publisher value="HL7 Switzerland"/>
    <contact>
        <name value="HL7 Switzerland"/>
        <telecom>
            <system value="url"/>
            <value value="https://www.hl7.ch/"/>
        </telecom>
    </contact>
    <description value="BFS Extension Admit Role for Encounter"/>
    <jurisdiction>
        <coding>
            <system value="urn:iso:std:iso:3166"/>
            <code value="CH"/>
        </coding>
    </jurisdiction>
    <fhirVersion value="4.0.1" />
    <kind value="complex-type"/>
    <abstract value="false"/>
    <context>
      <type value="element"/>
      <expression value="Encounter.hospitalization"/>
    </context>
    <type value="Extension"/>
    <baseDefinition value="http://hl7.org/fhir/StructureDefinition/Extension"/>
    <derivation value="constraint"/>
    <differential>
        <element id="Extension">
            <path value="Extension"/>
            <short value="Extension"/>
            <definition value="Extension"/>
            <min value="0"/>
            <max value="1"/>
        </element>
        <element id="Extension.extension">
            <path value="Extension.extension"/>
            <max value="0"/>
        </element>
        <element id="Extension.url">
            <path value="Extension.url"/>
            <type>
                <code value="uri"/>
            </type>
            <fixedUri value="http://fhir.ch/ig/ch-core/StructureDefinition/ch-ext-bfs-ms-admitrole"/>
        </element>
        <element id="Extension.valueCoding">
            <path value="Extension.valueCoding"/>
            <short value="Value of extension"/>
            <definition value="Value of extension - may be a resource or one of a constrained set of the data types (see
       Extensibility in the spec for list)."/>
            <min value="0"/>
            <max value="1"/>
            <type>
                <code value="Coding"/>
            </type>
            <isModifier value="false"/>
            <isSummary value="false"/>
            <binding>
                <strength value="required"/>
                <description value="A set of codes advising a system or user which name in a set of names to select for a
         given purpose."/>
                <valueSet value="http://fhir.ch/ig/ch-core/ValueSet/bfs-medstats-19-admitrole"/>
            </binding>
        </element>
    </differential>
</StructureDefinition> 